genpy/__init__.py
genpy/_keras.py
genpy/chooser.py
genpy/genetic.py
genpy/rules.py
genpy/simple_nn.py
genpy/track.py
genalgopy-1.0.0.dist-info/LICENSE
genalgopy-1.0.0.dist-info/METADATA
genalgopy-1.0.0.dist-info/WHEEL
genalgopy-1.0.0.dist-info/top_level.txt
genalgopy-1.0.0.dist-info/RECORD
