Metadata-Version: 2.1
Name: genalgopy
Version: 1.0.0
Summary: This package implements various classes and functions for genetic algorithms
Home-page: https://github.com/MrPoisen/Genetic_Algorithm_Python
Author: MrPoisen
License: UNKNOWN
Project-URL: Bug Tracker, https://github.com/pypa/Genetic_Algorithm_Python/issues
Keywords: genetic algorithm,evolution
Platform: UNKNOWN
Classifier: Programming Language :: Python :: 3
Classifier: License :: OSI Approved :: MIT License
Classifier: Operating System :: OS Independent
Requires-Python: >=3.6
License-File: LICENSE
